setup.cfg
setup.py
artie/__init__.py
artie/applications.py
artie/bot.py
artie/helpers.py
artie/settings.py
artie.egg-info/PKG-INFO
artie.egg-info/SOURCES.txt
artie.egg-info/dependency_links.txt
artie.egg-info/requires.txt
artie.egg-info/top_level.txt
bin/artie-run.py
test/tests.py