Metadata-Version: 1.0
Name: artie
Version: 0.1.1
Summary: IRC utility robot framework for Python
Home-page: http://github.com/sumeet/artie
Author: Sumeet Agarwal
Author-email: sumeet.a@gmail.com
License: UNKNOWN
Platform: UNKNOWN
Classifier: Development Status :: 3 - Alpha
Classifier: Environment :: No Input/Output (Daemon)
Classifier: Intended Audience :: Developers
Classifier: Intended Audience :: End Users/Desktop
Classifier: License :: OSI Approved :: MIT License
Classifier: Natural Language :: English
Classifier: Operating System :: POSIX
Classifier: Programming Language :: Python
Classifier: Topic :: Communications :: Chat :: Internet Relay Chat
